{
  "button_texture": {
    "type": "item",
    "res": "gtceu:empty_tier_i_battery"
  },
  "items": [
    "gtceu:empty_tier_i_battery",
    "gtceu:ev_lapotronic_battery",
    "gtceu:iv_lapotronic_battery",
    "gtceu:empty_tier_ii_battery",
    "gtceu:luv_lapotronic_battery",
    "gtceu:zpm_lapotronic_battery",
    "gtceu:empty_tier_iii_battery",
    "gtceu:uv_lapotronic_battery",
    "gtceu:uhv_ultimate_battery"
  ],
  "page": "gtceu:blocks/pss_battery",
  "position": [
    -50,
    0
  ],
  "section": "gtceu:blocks"
}