{
  "type": "gtceu:gt_recipe_serializer",
  "duration": 40,
  "inputs": {
    "item": [
      {
        "chance": 1.0,
        "content": {
          "type": "gtceu:sized",
          "count": 1,
          "fabric:type": "gtceu:sized",
          "ingredient": {
            "item": "minecraft:cobblestone"
          }
        }
      },
      {
        "chance": 1.0,
        "content": {
          "type": "gtceu:sized",
          "count": 1,
          "fabric:type": "gtceu:sized",
          "ingredient": {
            "item": "minecraft:vine"
          }
        }
      }
    ]
  },
  "outputs": {
    "item": [
      {
        "chance": 1.0,
        "content": {
          "type": "gtceu:sized",
          "count": 1,
          "fabric:type": "gtceu:sized",
          "ingredient": {
            "item": "minecraft:mossy_cobblestone"
          }
        }
      }
    ]
  },
  "recipe_type": "gtceu:assembler",
  "tickInputs": {
    "eu": [
      {
        "chance": 1.0,
        "content": 1
      }
    ]
  }
}