{
  "type": "gtceu:gt_recipe_serializer",
  "duration": 100,
  "inputs": {
    "item": [
      {
        "chance": 0.0,
        "content": {
          "type": "gtceu:sized",
          "count": 1,
          "fabric:type": "gtceu:sized",
          "ingredient": {
            "type": "forge:nbt",
            "count": 1,
            "item": "gtceu:circuit.integrated",
            "nbt": "{Configuration:1}"
          }
        }
      },
      {
        "chance": 1.0,
        "content": {
          "type": "gtceu:sized",
          "count": 1,
          "fabric:type": "gtceu:sized",
          "tag": "minecraft:wool"
        }
      },
      {
        "chance": 1.0,
        "content": {
          "type": "gtceu:sized",
          "count": 8,
          "fabric:type": "gtceu:sized",
          "ingredient": {
            "item": "minecraft:stick"
          }
        }
      }
    ]
  },
  "outputs": {
    "item": [
      {
        "chance": 1.0,
        "content": {
          "type": "gtceu:sized",
          "count": 1,
          "fabric:type": "gtceu:sized",
          "ingredient": {
            "item": "minecraft:painting"
          }
        }
      }
    ]
  },
  "recipe_type": "gtceu:assembler",
  "tickInputs": {
    "eu": [
      {
        "chance": 1.0,
        "content": 4
      }
    ]
  }
}