{
  "type": "gtceu:gt_recipe_serializer",
  "duration": 40,
  "inputs": {
    "item": [
      {
        "chance": 1.0,
        "content": {
          "type": "gtceu:sized",
          "count": 5,
          "fabric:type": "gtceu:sized",
          "ingredient": {
            "item": "minecraft:prismarine_crystals"
          }
        }
      },
      {
        "chance": 1.0,
        "content": {
          "type": "gtceu:sized",
          "count": 4,
          "fabric:type": "gtceu:sized",
          "ingredient": {
            "item": "minecraft:prismarine_shard"
          }
        }
      }
    ]
  },
  "outputs": {
    "item": [
      {
        "chance": 1.0,
        "content": {
          "type": "gtceu:sized",
          "count": 1,
          "fabric:type": "gtceu:sized",
          "ingredient": {
            "item": "minecraft:sea_lantern"
          }
        }
      }
    ]
  },
  "recipe_type": "gtceu:assembler",
  "tickInputs": {
    "eu": [
      {
        "chance": 1.0,
        "content": 4
      }
    ]
  }
}