<page>
  <h1>工具头和涡轮扇叶</h1>
  <h3>来源</h3>
  <text>
    <style color="0xaaaaaa" italic="true">作者：<style color="0xa4e7ff" hover-info="url" underlined="true" url-link="https://github.com/blackdragon2447">BlackDragon2447</style></style>
  </text>
  <h2>工具头</h2>
  <text>电动工具（目前尚未实现）拥有可更换的头部，电动工具的属性不仅取决于 <style color="0xafff00" hover-info="click link" link="gtceu:misc/power_unit" underlined="true">能量单元</style>，还取决于工具头。电动工具及其头部有五种类型，但要点都是一样的：工具的采矿等级和耐用性由其头部的材料决定。使用电动工具的好处是，它们的头部是可以更换的，因此，当你想升级能量单元时，可以转移头部，而当你想升级或弄坏头部时，就不需要新的能量单元了。</text>
  <!-- <text> -->
  <!--   <style color="0xcc8932">Tool stat comparison comming once electric tools are implemented.</style> -->
  <!-- </text> -->
  <h3>合成</h3>
  <text>所有工具头都需要手搓，但圆锯锯片除外，在某些情况下可以在<style color="0xafff00" hover-info="click link" link="gtceu:machines/lathe" underlined="true">车床</style>中用齿轮制作。配方中的钢部分与您要制作工具头的材料无关，并且始终存在。</text>
  <recipe id="gtceu:shaped/drill_head_aluminium"></recipe>
  <recipe id="gtceu:shaped/chainsaw_head_aluminium"></recipe>
  <recipe id="gtceu:shaped/buzzsaw_blade_aluminium"></recipe>
  <recipe id="gtceu:lathe/buzzsaw_gear_aluminium"></recipe>
  <recipe id="gtceu:shaped/wrench_head_aluminium"></recipe>
  <recipe id="gtceu:shaped/screwdriver_tip_aluminium"></recipe>
  <h2>涡轮扇叶</h2>
	Turbine blades are to turbines what tool heads are to electric tools, turbine blades determine a turbines Durability, Efficiency and Power.
	<h3>合成</h3>
	<text>涡轮扇叶既可手动制作，也可使用 <style color="0xafff00" hover-info="click link" link="gtceu:machines/forming_press" underlined="true">压模机</style>制作。</text>
  <recipe id="gtceu:shaped/turbine_blade_aluminium"></recipe>
  <recipe id="gtceu:forming_press/press_aluminium_turbine_rotor"></recipe>
</page>
