{
  "type": "gtceu:gt_recipe_serializer",
  "duration": 320,
  "inputs": {
    "fluid": [
      {
        "chance": 1.0,
        "content": {
          "amount": 3000,
          "fluid": "gtceu:green_sapphire_slurry"
        }
      }
    ]
  },
  "outputs": {
    "fluid": [
      {
        "chance": 1.0,
        "content": {
          "amount": 3000,
          "fluid": "gtceu:oxygen"
        }
      },
      {
        "chance": 1.0,
        "content": {
          "amount": 1000,
          "fluid": "gtceu:nitric_acid"
        }
      },
      {
        "chance": 1.0,
        "content": {
          "amount": 2000,
          "fluid": "gtceu:hydrochloric_acid"
        }
      }
    ],
    "item": [
      {
        "chance": 1.0,
        "content": {
          "type": "gtceu:sized",
          "count": 2,
          "fabric:type": "gtceu:sized",
          "ingredient": {
            "item": "gtceu:dust.aluminium"
          }
        }
      },
      {
        "chance": 0.2,
        "content": {
          "type": "gtceu:sized",
          "count": 1,
          "fabric:type": "gtceu:sized",
          "ingredient": {
            "item": "gtceu:dust_tiny.beryllium"
          }
        }
      },
      {
        "chance": 0.2,
        "content": {
          "type": "gtceu:sized",
          "count": 1,
          "fabric:type": "gtceu:sized",
          "ingredient": {
            "item": "gtceu:dust_tiny.titanium"
          }
        }
      },
      {
        "chance": 0.2,
        "content": {
          "type": "gtceu:sized",
          "count": 1,
          "fabric:type": "gtceu:sized",
          "ingredient": {
            "item": "gtceu:dust_tiny.iron"
          }
        }
      },
      {
        "chance": 0.2,
        "content": {
          "type": "gtceu:sized",
          "count": 1,
          "fabric:type": "gtceu:sized",
          "ingredient": {
            "item": "gtceu:dust_tiny.vanadium"
          }
        }
      }
    ]
  },
  "recipe_type": "gtceu:centrifuge",
  "tickInputs": {
    "eu": [
      {
        "chance": 1.0,
        "content": 480
      }
    ]
  }
}