{
  "type": "gtceu:gt_recipe_serializer",
  "duration": 400,
  "inputs": {
    "fluid": [
      {
        "chance": 1.0,
        "content": {
          "amount": 24,
          "fluid": "gtceu:acidic_osmium_solution"
        }
      }
    ]
  },
  "outputs": {
    "fluid": [
      {
        "chance": 1.0,
        "content": {
          "amount": 12,
          "fluid": "gtceu:hydrochloric_acid"
        }
      },
      {
        "chance": 1.0,
        "content": {
          "amount": 12,
          "fluid": "minecraft:water"
        }
      }
    ],
    "item": [
      {
        "chance": 1.0,
        "content": {
          "type": "gtceu:sized",
          "count": 5,
          "fabric:type": "gtceu:sized",
          "ingredient": {
            "item": "gtceu:dust.osmium_tetroxide"
          }
        }
      }
    ]
  },
  "recipe_type": "gtceu:distillation_tower",
  "tickInputs": {
    "eu": [
      {
        "chance": 1.0,
        "content": 120
      }
    ]
  }
}