{
  "type": "gtceu:gt_recipe_serializer",
  "duration": 600,
  "inputs": {
    "fluid": [
      {
        "chance": 1.0,
        "content": {
          "amount": 7,
          "fluid": "gtceu:soldering_alloy"
        }
      },
      {
        "chance": 1.0,
        "content": {
          "amount": 12,
          "fluid": "gtceu:lubricant"
        }
      },
      {
        "chance": 1.0,
        "content": {
          "amount": 7,
          "fluid": "gtceu:naquadria"
        }
      }
    ],
    "item": [
      {
        "chance": 1.0,
        "content": {
          "item": "gtceu:electric.motor.uv"
        }
      },
      {
        "chance": 1.0,
        "content": {
          "type": "gtceu:sized",
          "count": 4,
          "fabric:type": "gtceu:sized",
          "tag": "c:tritanium_plates"
        }
      },
      {
        "chance": 1.0,
        "content": {
          "type": "gtceu:sized",
          "count": 4,
          "fabric:type": "gtceu:sized",
          "tag": "c:tritanium_rings"
        }
      },
      {
        "chance": 1.0,
        "content": {
          "type": "gtceu:sized",
          "count": 16,
          "fabric:type": "gtceu:sized",
          "tag": "c:tritanium_rounds"
        }
      },
      {
        "chance": 1.0,
        "content": {
          "type": "gtceu:sized",
          "count": 4,
          "fabric:type": "gtceu:sized",
          "tag": "c:tritanium_rods"
        }
      },
      {
        "chance": 1.0,
        "content": {
          "type": "gtceu:sized",
          "count": 1,
          "fabric:type": "gtceu:sized",
          "tag": "c:naquadah_alloy_gears"
        }
      },
      {
        "chance": 1.0,
        "content": {
          "type": "gtceu:sized",
          "count": 2,
          "fabric:type": "gtceu:sized",
          "tag": "c:naquadah_alloy_small_gears"
        }
      },
      {
        "chance": 1.0,
        "content": {
          "type": "gtceu:sized",
          "count": 2,
          "fabric:type": "gtceu:sized",
          "ingredient": {
            "item": "gtceu:cable_single.yttrium_barium_cuprate"
          }
        }
      }
    ]
  },
  "outputs": {
    "item": [
      {
        "chance": 1.0,
        "content": {
          "type": "gtceu:sized",
          "count": 1,
          "fabric:type": "gtceu:sized",
          "ingredient": {
            "item": "gtceu:electric.piston.uv"
          }
        }
      }
    ]
  },
  "recipe_type": "gtceu:assembly_line",
  "tickInputs": {
    "eu": [
      {
        "chance": 1.0,
        "content": 100000
      }
    ]
  }
}