{
  "type": "minecraft:crafting_shapeless",
  "ingredients": [
    {
      "item": "gtceu:credit.silver"
    },
    {
      "item": "gtceu:credit.silver"
    },
    {
      "item": "gtceu:credit.silver"
    },
    {
      "item": "gtceu:credit.silver"
    },
    {
      "item": "gtceu:credit.silver"
    },
    {
      "item": "gtceu:credit.silver"
    },
    {
      "item": "gtceu:credit.silver"
    },
    {
      "item": "gtceu:credit.silver"
    }
  ],
  "result": {
    "item": "gtceu:credit.gold"
  }
}