<page>
 <h1>
  Machine Hull
 </h1>
 <h3>
  Source
 </h3>
 <text><style color="0xaaaaaa" italic="true">Note: this page is ported from MCMOD's GTCEu wiki.<br/>Author: <style color="0xa4e7ff" hover-info="url" underlined="true" url-link="https://center.mcmod.cn/179043/">花海</style>, <style color="0xa4e7ff" hover-info="url" underlined="true" url-link="https://center.mcmod.cn/119280/">Oganesson897</style><br/></style></text>
 <h2 font-color="0xff0000">
  WARNING!!!
 </h2>
 <text isCenter="true">
  <style color="0xff0000">The warning means this is not a reliable page.</style>
  <br/>
  <style bold="true" color="0xffaa00">Please do not report any mistakes on the page, either discord or github.</style>
  <br/>
  This page is translated from the Chinese wiki which hasn't been reviewed and polished yet. It may contain errors and inaccuracies. We are looking forward to your help by improving this page.
 </text>
 <text>
  <br/>
  <style>
   N
   <style color="0xaaaaaa" italic="true">-You need an unbelievable imagination to use it.</style>
   N
   <br/>
   N
  </style>
  <br/>
  <br/>
  <style>
   @ n @ Mechanical Blocks at @ n @
   <style color="0xafff00" hover-info="click link" link="gtceu:links" underlined="true">assembly machine</style>
   @ n @ by 1 corresponding voltage level in @ n @
   <style color="0xafff00" hover-info="click link" link="gtceu:links" underlined="true">Mechanical Casing</style>
   @ n @, made of 2 1x cables corresponding to the voltage level and molten plastic for the 288 L corresponding voltage level, can be made into mechanical blocks of all grades with only the LV level voltage. at @ n @
   <style color="0xafff00" hover-info="click link" link="gtceu:links" underlined="true">Home</style>
   It can also be directly synthesized in @ n @, but in addition to the above-mentioned equivalent amount of material, an additional metal plate corresponding to the voltage level needs to be consumed to be made. @ n @
  </style>
  <br/>
  <br/>
  <style>
   @ n @ All single-block machines and multi-block machines are generally composed of blocks, such as @ n @
   <style color="0xafff00" hover-info="click link" link="gtceu:links" underlined="true">Input warehouse</style>
   In @ n @, the glass tube can participate in the use of @ n @
   <style color="0xafff00" hover-info="click link" link="gtceu:links" underlined="true">Output warehouse</style>
   n, n
   <style color="0xafff00" hover-info="click link" link="gtceu:links" underlined="true">@ n @ Tungsten Carbide - TungstenCarbide @ n @</style>
   n, n
   <style color="0xafff00" hover-info="click link" link="gtceu:links" underlined="true">Output bus</style>
   n, n
   <style color="0xafff00" hover-info="click link" link="gtceu:links" underlined="true">Energy warehouse</style>
   The assembly of machines such as @ n @ requires the use of 1 mechanical block of the corresponding grade. Extra mechanical blocks can also be used in @ n @
   <style color="0xafff00" hover-info="click link" link="gtceu:links" underlined="true">lapping machine</style>
   @ n @ or @ n @
   <style color="0xafff00" hover-info="click link" link="gtceu:links" underlined="true">Electric arc furnace</style>
   Recycled in @ n @ (with oxygen), most of the synthetic raw materials are recovered, and only the LV level voltage is required for operation. @ n @
  </style>
  <br/>
 </text>
</page>
